hdwallets/__init__.py
hdwallets/_bip32.py
hdwallets/_utils.py
hdwallets/py.typed
hdwallets-0.1.1.dist-info/LICENSE
hdwallets-0.1.1.dist-info/WHEEL
hdwallets-0.1.1.dist-info/METADATA
hdwallets-0.1.1.dist-info/RECORD
