Metadata-Version: 2.1
Name: hdwallets
Version: 0.1.1
Summary: Python implementation of the BIP32 key derivation scheme
Home-page: https://github.com/hukkinj1/hdwallets
License: BSD-3-Clause
Keywords: bip32,hierarchical,deterministic,wallets,bitcoin
Author: hukkinj1
Author-email: hukkinj1@users.noreply.github.com
Requires-Python: >=3.6,<4.0
Classifier: Intended Audience :: Developers
Classifier: License :: OSI Approved :: BSD License
Classifier: Natural Language :: English
Classifier: Programming Language :: Python :: 3
Classifier: Programming Language :: Python :: 3.6
Classifier: Programming Language :: Python :: 3.7
Classifier: Programming Language :: Python :: 3.8
Classifier: Topic :: Software Development :: Libraries :: Python Modules
Classifier: Typing :: Typed
Requires-Dist: ecdsa (>=0.14.0,<0.17.0)
Project-URL: Changelog, https://github.com/hukkinj1/hdwallets/blob/master/CHANGELOG.md
Project-URL: Repository, https://github.com/hukkinj1/hdwallets
